krescope/__init__.py
krescope/analyzer.py
krescope/cli.py
krescope/exceptions.py
krescope/k8s_client.py
krescope/models.py
krescope/version.py
krescope-1.0.1.dist-info/licenses/LICENSE
krescope-1.0.1.dist-info/METADATA
krescope-1.0.1.dist-info/WHEEL
krescope-1.0.1.dist-info/entry_points.txt
krescope-1.0.1.dist-info/top_level.txt
krescope-1.0.1.dist-info/RECORD
