Metadata-Version: 2.4
Name: krescope
Version: 1.0.1
Summary: Kubernetes Resource Optimizer - Analyze & recommend CPU/Memory requests/limits
Author: Rohan Rustagi
License: MIT
Classifier: Development Status :: 4 - Beta
Classifier: Intended Audience :: Developers
Classifier: Intended Audience :: System Administrators
Classifier: Programming Language :: Python :: 3
Classifier: Topic :: Software Development :: Libraries :: Python Modules
Classifier: Topic :: System :: Systems Administration
Requires-Python: >=3.8
License-File: LICENSE
Requires-Dist: kubernetes>=24.2.0
Requires-Dist: click>=8.0.0
Requires-Dist: typing-extensions>=4.0
Requires-Dist: rich>=12.0.0
Dynamic: license-file
Dynamic: requires-python
